{
  "variants": {
    "east=false,north=false,south=false,waterlogged=false,west=false": {
      "model": "premierpainmod:block/sandstone_villager_table_solo"
    },
    "east=false,north=false,south=false,waterlogged=false,west=true": {
      "model": "premierpainmod:block/sandstone_villager_table_duo_w",
      "y": 180
    },
    "east=false,north=false,south=false,waterlogged=true,west=false": {
      "model": "premierpainmod:block/sandstone_villager_table_solo"
    },
    "east=false,north=false,south=false,waterlogged=true,west=true": {
      "model": "premierpainmod:block/sandstone_villager_table_duo_w",
      "y": 180
    },
    "east=false,north=false,south=true,waterlogged=false,west=false": {
      "model": "premierpainmod:block/sandstone_villager_table_duo_s",
      "y": 90
    },
    "east=false,north=false,south=true,waterlogged=false,west=true": {
      "model": "premierpainmod:block/sandstone_villager_table_trio_sw",
      "y": 90
    },
    "east=false,north=false,south=true,waterlogged=true,west=false": {
      "model": "premierpainmod:block/sandstone_villager_table_duo_s",
      "y": 90
    },
    "east=false,north=false,south=true,waterlogged=true,west=true": {
      "model": "premierpainmod:block/sandstone_villager_table_trio_sw",
      "y": 90
    },
    "east=false,north=true,south=false,waterlogged=false,west=false": {
      "model": "premierpainmod:block/sandstone_villager_table_duo_n",
      "y": 270
    },
    "east=false,north=true,south=false,waterlogged=false,west=true": {
      "model": "premierpainmod:block/sandstone_villager_table_trio_nw",
      "y": 180
    },
    "east=false,north=true,south=false,waterlogged=true,west=false": {
      "model": "premierpainmod:block/sandstone_villager_table_duo_n",
      "y": 270
    },
    "east=false,north=true,south=false,waterlogged=true,west=true": {
      "model": "premierpainmod:block/sandstone_villager_table_trio_nw",
      "y": 180
    },
    "east=false,north=true,south=true,waterlogged=false,west=false": {
      "model": "premierpainmod:block/sandstone_villager_table_trio_ns",
      "y": 90
    },
    "east=false,north=true,south=true,waterlogged=false,west=true": {
      "model": "premierpainmod:block/sandstone_villager_table_quatuor_swn",
      "y": 90
    },
    "east=false,north=true,south=true,waterlogged=true,west=false": {
      "model": "premierpainmod:block/sandstone_villager_table_trio_ns",
      "y": 90
    },
    "east=false,north=true,south=true,waterlogged=true,west=true": {
      "model": "premierpainmod:block/sandstone_villager_table_quatuor_swn",
      "y": 90
    },
    "east=true,north=false,south=false,waterlogged=false,west=false": {
      "model": "premierpainmod:block/sandstone_villager_table_duo_e"
    },
    "east=true,north=false,south=false,waterlogged=false,west=true": {
      "model": "premierpainmod:block/sandstone_villager_table_trio_we"
    },
    "east=true,north=false,south=false,waterlogged=true,west=false": {
      "model": "premierpainmod:block/sandstone_villager_table_duo_e"
    },
    "east=true,north=false,south=false,waterlogged=true,west=true": {
      "model": "premierpainmod:block/sandstone_villager_table_trio_we"
    },
    "east=true,north=false,south=true,waterlogged=false,west=false": {
      "model": "premierpainmod:block/sandstone_villager_table_trio_se"
    },
    "east=true,north=false,south=true,waterlogged=false,west=true": {
      "model": "premierpainmod:block/sandstone_villager_table_quatuor_esw"
    },
    "east=true,north=false,south=true,waterlogged=true,west=false": {
      "model": "premierpainmod:block/sandstone_villager_table_trio_se"
    },
    "east=true,north=false,south=true,waterlogged=true,west=true": {
      "model": "premierpainmod:block/sandstone_villager_table_quatuor_esw"
    },
    "east=true,north=true,south=false,waterlogged=false,west=false": {
      "model": "premierpainmod:block/sandstone_villager_table_trio_ne",
      "y": 270
    },
    "east=true,north=true,south=false,waterlogged=false,west=true": {
      "model": "premierpainmod:block/sandstone_villager_table_quatuor_wne",
      "y": 180
    },
    "east=true,north=true,south=false,waterlogged=true,west=false": {
      "model": "premierpainmod:block/sandstone_villager_table_trio_ne",
      "y": 270
    },
    "east=true,north=true,south=false,waterlogged=true,west=true": {
      "model": "premierpainmod:block/sandstone_villager_table_quatuor_wne",
      "y": 180
    },
    "east=true,north=true,south=true,waterlogged=false,west=false": {
      "model": "premierpainmod:block/sandstone_villager_table_quatuor_nes",
      "y": 270
    },
    "east=true,north=true,south=true,waterlogged=false,west=true": {
      "model": "premierpainmod:block/sandstone_villager_table_pentuor"
    },
    "east=true,north=true,south=true,waterlogged=true,west=false": {
      "model": "premierpainmod:block/sandstone_villager_table_quatuor_nes",
      "y": 270
    },
    "east=true,north=true,south=true,waterlogged=true,west=true": {
      "model": "premierpainmod:block/sandstone_villager_table_pentuor"
    }
  }
}